{"config":{"output_file":null,"full_docs":false,"pub_only":true,"reachable_only":true,"distro_crate":false,"signatures":false,"borrow_data":false},"version":"0.19.1","compilation":{"directory":"/Users/jwen/.cargo/registry/src/github.com-1ecc6299db9ec823/candid-0.6.21","program":"/Users/jwen/.rustup/toolchains/stable-x86_64-apple-darwin/bin/rls","arguments":["--crate-name","build_script_build","--edition=2018","/Users/jwen/.cargo/registry/src/github.com-1ecc6299db9ec823/candid-0.6.21/build.rs","--json=diagnostic-rendered-ansi","--crate-type","bin","--emit=dep-info,link","-C","embed-bitcode=no","-C","split-debuginfo=unpacked","-C","debuginfo=2","--cfg","feature=\"cdk\"","-C","metadata=f346f2bea58528ec","-C","extra-filename=-f346f2bea58528ec","--out-dir","/Users/jwen/workspace/dmail/dfinity-react-wanxiang/backend/target/rls/debug/build/candid-f346f2bea58528ec","-L","dependency=/Users/jwen/workspace/dmail/dfinity-react-wanxiang/backend/target/rls/debug/deps","--extern","lalrpop=/Users/jwen/workspace/dmail/dfinity-react-wanxiang/backend/target/rls/debug/deps/liblalrpop-895840dcf879520d.rlib","--cap-lints","allow","--error-format=json","--sysroot","/Users/jwen/.rustup/toolchains/stable-x86_64-apple-darwin"],"output":"/Users/jwen/workspace/dmail/dfinity-react-wanxiang/backend/target/rls/debug/build/candid-f346f2bea58528ec/build_script_build-f346f2bea58528ec"},"prelude":{"crate_id":{"name":"build_script_build","disambiguator":[9385900978122765218,0]},"crate_root":"/Users/jwen/.cargo/registry/src/github.com-1ecc6299db9ec823/candid-0.6.21","external_crates":[{"file_name":"/Users/jwen/.cargo/registry/src/github.com-1ecc6299db9ec823/candid-0.6.21/build.rs","num":1,"id":{"name":"std","disambiguator":[7777094053559708767,0]}},{"file_name":"/Users/jwen/.cargo/registry/src/github.com-1ecc6299db9ec823/candid-0.6.21/build.rs","num":2,"id":{"name":"core","disambiguator":[10550174156715778454,0]}},{"file_name":"/Users/jwen/.cargo/registry/src/github.com-1ecc6299db9ec823/candid-0.6.21/build.rs","num":3,"id":{"name":"compiler_builtins","disambiguator":[8770346864682343241,0]}},{"file_name":"/Users/jwen/.cargo/registry/src/github.com-1ecc6299db9ec823/candid-0.6.21/build.rs","num":4,"id":{"name":"rustc_std_workspace_core","disambiguator":[8196830942918118636,0]}},{"file_name":"/Users/jwen/.cargo/registry/src/github.com-1ecc6299db9ec823/candid-0.6.21/build.rs","num":5,"id":{"name":"alloc","disambiguator":[12786826162718588903,0]}},{"file_name":"/Users/jwen/.cargo/registry/src/github.com-1ecc6299db9ec823/candid-0.6.21/build.rs","num":6,"id":{"name":"libc","disambiguator":[7262382603413566750,0]}},{"file_name":"/Users/jwen/.cargo/registry/src/github.com-1ecc6299db9ec823/candid-0.6.21/build.rs","num":7,"id":{"name":"unwind","disambiguator":[12233289566066112318,0]}},{"file_name":"/Users/jwen/.cargo/registry/src/github.com-1ecc6299db9ec823/candid-0.6.21/build.rs","num":8,"id":{"name":"cfg_if","disambiguator":[4998072162051350919,0]}},{"file_name":"/Users/jwen/.cargo/registry/src/github.com-1ecc6299db9ec823/candid-0.6.21/build.rs","num":9,"id":{"name":"hashbrown","disambiguator":[14817392966914922723,0]}},{"file_name":"/Users/jwen/.cargo/registry/src/github.com-1ecc6299db9ec823/candid-0.6.21/build.rs","num":10,"id":{"name":"rustc_std_workspace_alloc","disambiguator":[13537029249427453884,0]}},{"file_name":"/Users/jwen/.cargo/registry/src/github.com-1ecc6299db9ec823/candid-0.6.21/build.rs","num":11,"id":{"name":"rustc_demangle","disambiguator":[16172866892641339196,0]}},{"file_name":"/Users/jwen/.cargo/registry/src/github.com-1ecc6299db9ec823/candid-0.6.21/build.rs","num":12,"id":{"name":"std_detect","disambiguator":[18226255698322429307,0]}},{"file_name":"/Users/jwen/.cargo/registry/src/github.com-1ecc6299db9ec823/candid-0.6.21/build.rs","num":13,"id":{"name":"addr2line","disambiguator":[12872472635654720224,0]}},{"file_name":"/Users/jwen/.cargo/registry/src/github.com-1ecc6299db9ec823/candid-0.6.21/build.rs","num":14,"id":{"name":"gimli","disambiguator":[15477836623066676988,0]}},{"file_name":"/Users/jwen/.cargo/registry/src/github.com-1ecc6299db9ec823/candid-0.6.21/build.rs","num":15,"id":{"name":"object","disambiguator":[8883445751219211826,0]}},{"file_name":"/Users/jwen/.cargo/registry/src/github.com-1ecc6299db9ec823/candid-0.6.21/build.rs","num":16,"id":{"name":"panic_unwind","disambiguator":[4189598673803333586,0]}},{"file_name":"/Users/jwen/.cargo/registry/src/github.com-1ecc6299db9ec823/candid-0.6.21/build.rs","num":17,"id":{"name":"lalrpop","disambiguator":[11414603773221932649,0]}},{"file_name":"/Users/jwen/.cargo/registry/src/github.com-1ecc6299db9ec823/candid-0.6.21/build.rs","num":18,"id":{"name":"ascii_canvas","disambiguator":[4563055189808505839,0]}},{"file_name":"/Users/jwen/.cargo/registry/src/github.com-1ecc6299db9ec823/candid-0.6.21/build.rs","num":19,"id":{"name":"term","disambiguator":[15000911653721341640,0]}},{"file_name":"/Users/jwen/.cargo/registry/src/github.com-1ecc6299db9ec823/candid-0.6.21/build.rs","num":20,"id":{"name":"dirs_next","disambiguator":[16804742946200624504,0]}},{"file_name":"/Users/jwen/.cargo/registry/src/github.com-1ecc6299db9ec823/candid-0.6.21/build.rs","num":21,"id":{"name":"cfg_if","disambiguator":[10867537363686058513,0]}},{"file_name":"/Users/jwen/.cargo/registry/src/github.com-1ecc6299db9ec823/candid-0.6.21/build.rs","num":22,"id":{"name":"dirs_sys_next","disambiguator":[10324659608212435403,0]}},{"file_name":"/Users/jwen/.cargo/registry/src/github.com-1ecc6299db9ec823/candid-0.6.21/build.rs","num":23,"id":{"name":"libc","disambiguator":[11570554969091148837,0]}},{"file_name":"/Users/jwen/.cargo/registry/src/github.com-1ecc6299db9ec823/candid-0.6.21/build.rs","num":24,"id":{"name":"atty","disambiguator":[1656316126709756230,0]}},{"file_name":"/Users/jwen/.cargo/registry/src/github.com-1ecc6299db9ec823/candid-0.6.21/build.rs","num":25,"id":{"name":"bit_set","disambiguator":[4851947180085104249,0]}},{"file_name":"/Users/jwen/.cargo/registry/src/github.com-1ecc6299db9ec823/candid-0.6.21/build.rs","num":26,"id":{"name":"bit_vec","disambiguator":[12198264292519360666,0]}},{"file_name":"/Users/jwen/.cargo/registry/src/github.com-1ecc6299db9ec823/candid-0.6.21/build.rs","num":27,"id":{"name":"diff","disambiguator":[2327387231904658084,0]}},{"file_name":"/Users/jwen/.cargo/registry/src/github.com-1ecc6299db9ec823/candid-0.6.21/build.rs","num":28,"id":{"name":"ena","disambiguator":[14313264390230899837,0]}},{"file_name":"/Users/jwen/.cargo/registry/src/github.com-1ecc6299db9ec823/candid-0.6.21/build.rs","num":29,"id":{"name":"log","disambiguator":[7215877964631658135,0]}},{"file_name":"/Users/jwen/.cargo/registry/src/github.com-1ecc6299db9ec823/candid-0.6.21/build.rs","num":30,"id":{"name":"itertools","disambiguator":[18076659142369666816,0]}},{"file_name":"/Users/jwen/.cargo/registry/src/github.com-1ecc6299db9ec823/candid-0.6.21/build.rs","num":31,"id":{"name":"either","disambiguator":[16278877783919247124,0]}},{"file_name":"/Users/jwen/.cargo/registry/src/github.com-1ecc6299db9ec823/candid-0.6.21/build.rs","num":32,"id":{"name":"petgraph","disambiguator":[15719172882858050364,0]}},{"file_name":"/Users/jwen/.cargo/registry/src/github.com-1ecc6299db9ec823/candid-0.6.21/build.rs","num":33,"id":{"name":"fixedbitset","disambiguator":[11180260702222105072,0]}},{"file_name":"/Users/jwen/.cargo/registry/src/github.com-1ecc6299db9ec823/candid-0.6.21/build.rs","num":34,"id":{"name":"indexmap","disambiguator":[17547845773284579928,0]}},{"file_name":"/Users/jwen/.cargo/registry/src/github.com-1ecc6299db9ec823/candid-0.6.21/build.rs","num":35,"id":{"name":"hashbrown","disambiguator":[13079448545070024900,0]}},{"file_name":"/Users/jwen/.cargo/registry/src/github.com-1ecc6299db9ec823/candid-0.6.21/build.rs","num":36,"id":{"name":"regex_syntax","disambiguator":[9491244640211615020,0]}},{"file_name":"/Users/jwen/.cargo/registry/src/github.com-1ecc6299db9ec823/candid-0.6.21/build.rs","num":37,"id":{"name":"regex","disambiguator":[17114719222746324020,0]}},{"file_name":"/Users/jwen/.cargo/registry/src/github.com-1ecc6299db9ec823/candid-0.6.21/build.rs","num":38,"id":{"name":"aho_corasick","disambiguator":[10129043331075894290,0]}},{"file_name":"/Users/jwen/.cargo/registry/src/github.com-1ecc6299db9ec823/candid-0.6.21/build.rs","num":39,"id":{"name":"memchr","disambiguator":[9310436094961861381,0]}},{"file_name":"/Users/jwen/.cargo/registry/src/github.com-1ecc6299db9ec823/candid-0.6.21/build.rs","num":40,"id":{"name":"string_cache","disambiguator":[5314774657267118769,0]}},{"file_name":"/Users/jwen/.cargo/registry/src/github.com-1ecc6299db9ec823/candid-0.6.21/build.rs","num":41,"id":{"name":"debug_unreachable","disambiguator":[13767219904714410617,0]}},{"file_name":"/Users/jwen/.cargo/registry/src/github.com-1ecc6299db9ec823/candid-0.6.21/build.rs","num":42,"id":{"name":"phf_shared","disambiguator":[9126572122417810946,0]}},{"file_name":"/Users/jwen/.cargo/registry/src/github.com-1ecc6299db9ec823/candid-0.6.21/build.rs","num":43,"id":{"name":"siphasher","disambiguator":[10744715850761267920,0]}},{"file_name":"/Users/jwen/.cargo/registry/src/github.com-1ecc6299db9ec823/candid-0.6.21/build.rs","num":44,"id":{"name":"lazy_static","disambiguator":[3505520028844614710,0]}},{"file_name":"/Users/jwen/.cargo/registry/src/github.com-1ecc6299db9ec823/candid-0.6.21/build.rs","num":45,"id":{"name":"parking_lot","disambiguator":[16881688203467579132,0]}},{"file_name":"/Users/jwen/.cargo/registry/src/github.com-1ecc6299db9ec823/candid-0.6.21/build.rs","num":46,"id":{"name":"instant","disambiguator":[18321594290740049838,0]}},{"file_name":"/Users/jwen/.cargo/registry/src/github.com-1ecc6299db9ec823/candid-0.6.21/build.rs","num":47,"id":{"name":"lock_api","disambiguator":[7930544010720259573,0]}},{"file_name":"/Users/jwen/.cargo/registry/src/github.com-1ecc6299db9ec823/candid-0.6.21/build.rs","num":48,"id":{"name":"scopeguard","disambiguator":[210853324482982727,0]}},{"file_name":"/Users/jwen/.cargo/registry/src/github.com-1ecc6299db9ec823/candid-0.6.21/build.rs","num":49,"id":{"name":"parking_lot_core","disambiguator":[11361161633790053716,0]}},{"file_name":"/Users/jwen/.cargo/registry/src/github.com-1ecc6299db9ec823/candid-0.6.21/build.rs","num":50,"id":{"name":"smallvec","disambiguator":[16442315623094096331,0]}},{"file_name":"/Users/jwen/.cargo/registry/src/github.com-1ecc6299db9ec823/candid-0.6.21/build.rs","num":51,"id":{"name":"precomputed_hash","disambiguator":[16173890397250850041,0]}},{"file_name":"/Users/jwen/.cargo/registry/src/github.com-1ecc6299db9ec823/candid-0.6.21/build.rs","num":52,"id":{"name":"tiny_keccak","disambiguator":[7179115818492485617,0]}},{"file_name":"/Users/jwen/.cargo/registry/src/github.com-1ecc6299db9ec823/candid-0.6.21/build.rs","num":53,"id":{"name":"crunchy","disambiguator":[11877742581524084252,0]}},{"file_name":"/Users/jwen/.cargo/registry/src/github.com-1ecc6299db9ec823/candid-0.6.21/build.rs","num":54,"id":{"name":"unicode_xid","disambiguator":[18407250905872736045,0]}},{"file_name":"/Users/jwen/.cargo/registry/src/github.com-1ecc6299db9ec823/candid-0.6.21/build.rs","num":55,"id":{"name":"lalrpop_util","disambiguator":[7583760388790103172,0]}}],"span":{"file_name":"/Users/jwen/.cargo/registry/src/github.com-1ecc6299db9ec823/candid-0.6.21/build.rs","byte_start":0,"byte_end":192,"line_start":1,"line_end":7,"column_start":1,"column_end":2}},"imports":[],"defs":[{"kind":"Mod","id":{"krate":0,"index":0},"span":{"file_name":"/Users/jwen/.cargo/registry/src/github.com-1ecc6299db9ec823/candid-0.6.21/build.rs","byte_start":0,"byte_end":192,"line_start":1,"line_end":7,"column_start":1,"column_end":2},"name":"","qualname":"::","value":"/Users/jwen/.cargo/registry/src/github.com-1ecc6299db9ec823/candid-0.6.21/build.rs","parent":null,"children":[{"krate":0,"index":1},{"krate":0,"index":2},{"krate":0,"index":3}],"decl_id":null,"docs":"","sig":null,"attributes":[]}],"impls":[],"refs":[],"macro_refs":[],"relations":[]}